zsocket/__init__.py
zsocket/commonlib/__init__.py
zsocket/commonlib/data_pack.py
zsocket/commonlib/utils.py
zsocket/config/__init__.py
zsocket/config/mconfig.py
zsocket/tcp/__init__.py
zsocket/tcp/client.py
zsocket/tcp/server.py
zsocket/tcp_base/__init__.py
zsocket/tcp_base/client_base.py
zsocket/tcp_base/server_base.py
zsocket/udp_base/__init__.py
zsocket/udp_base/client_base.py
zsocket/udp_base/server_base.py
zsocket-1.0.3.data/scripts/description.txt
zsocket-1.0.3.dist-info/METADATA
zsocket-1.0.3.dist-info/RECORD
zsocket-1.0.3.dist-info/WHEEL
zsocket-1.0.3.dist-info/top_level.txt
